{"5bGbpgjrYy9zqWB0cqHsCQ==":"agustinisrael-logo-96x105.png","phlNxxPTXIoXY4i6WqTTSA==":"agustin-israel-foto-perfil-lunar-l-2000x1136.jpg","tAjhkMEX8SeiLjMUEKVLlA==":"agustin-israel-foto-perfil-header-l-2000x1136.jpg","uycc5Nc4V80WVGPNm3z2+Q==":"agustin-israel-foto-perfil-header-2000x1135.jpg","twXDo2AFszcUSLsPvR4cpA==":"agustin-israel-foto-perfil-header-l-2000x1135.jpg","RhGPQfEn1/qWnrjuajgx/A==":"agustin-israel-sevilla-en-fiestas-960x952.jpeg","V5eQadVTcWX+KBRBjfROvg==":"mbr-1101x734.jpg","4oErOzBspLYbuyg/kskMKw==":"mbr-1-1101x734.jpg","4gfOEFek4U5K5CA/bYStbQ==":"agustinisrael--fiestasdeprimavera-1197x1807.jpg","t0+qAERmYjgkKpdDzvfpfA==":"agustinisrael-currografia-598x987.jpg","mmTeHEu5jCgB0gBL4U9D6Q==":"agustinisrael-prohibido-adelantamiento-537x537.jpg","DeN0p8FR3xcg6jTwrO5Lhg==":"agustinisrael-capitan-nazareno-591x1163.jpg","XbYkqnGBHkyzt2JD32JcEw==":"agustinisrael-selfie-1349x1349.jpg","P4S8oy5RHOtLCQxWTBOnFQ==":"agustinisrael-haring-sevilla-sanlucar%20copia-1349x1932.jpg","mRWk51/HOVrL43CUjnOpTw==":"agustinisrael-abril-814x1100.jpg","c7zFS4epR0FbDGpNEERwTg==":"agustinisrael-escultura-814x543.jpg","NTIZCxnlTiC+Cn6o8jnK0A==":"agustinisrael-foto-el-dia-mas-feliz-de-nuestra-vida-389x389.jpg","4tlOr08oqOHZMdGINZO9pw==":"agustinisrael-carteles-358x512.jpg","VnCvp60+Mz0tODW8QRk+aA==":"agustinisrael-capitan-nazareno-portada-1161x871.png","ieZzvmmiZ3w04LKuW9VhSg==":"agustinisrael-tesis-portada-1161x653.png","+y/sBjq0KZc7eBPeAI0eRw==":"agustinisrael-tesis-portada-s-822x989.png","sTQziNjt+Uqd1nliBy4YzA==":"agustinisrael-capitan-nazareno-portada%20copyl-1161x1562.jpeg","aMlc8tzcubTCOqs2/TgtRQ==":"agustinisrael-tesis-portada-l-696x980.png","Oppyk4uhm5VpcE0m/tU7ug==":"agustin-israel-header-autoretrato-2000x1974.jpg","fuBaNYdj677q+iC1oMXLUQ==":"logo-institucion-1-300x300.jpg","2mg6y5Zx5lZ5cMTWvmis7A==":"logo-institucion-3-300x300.jpg","ffCH2ch7Hw4eLwRVLtWxKw==":"logo-institucion-5-300x300.jpg","urbqVcp3yeG8j0fM3TzrDA==":"logo-institucion-7-300x300.jpg","cmi1FZ5grVBq2D8z7opjRQ==":"logo-institucion-10-300x300.jpg","qUqGN23ABLhpi42vPXnAsw==":"logo-institucion-9-300x300.jpg","hUMBbWMsSI6ry9jPkUfkEA==":"logo-institucion-6-300x300.jpg","sUNqsefByVq27eYjNSJe6Q==":"logo-institucion-2-300x300.jpg","rfKzJ5p00nLBaNsTCzO9bQ==":"logo-institucion-11-300x300.jpg","i6iWbikxGz6JYMfqLDqOiw==":"grupo.investigacion-337-300x300.jpg","QbawCVXrvtTs2DW6o3Oq5A==":"magasse-300x300.jpg","o7MNW0Y8fAypUyixVwiIxA==":"hum-337-agustin-israel-h-1497x1059.jpg","QsRE8zpEFWFeNPfpeTAu3w==":"grabado%20agustinisrael-841x1027.jpeg","tJUHN5/4o56yGxYafsfLsg==":"cartel%20arahal-2021-encargo%20festial%20algurugu%CC%81-713x1027.jpg","kPP/sjmNOJWIegJSoFXwXg==":"tondo%20moron-adquisicio%CC%81n%20coleccio%CC%81n%20municipal%20de%20arte%20de%20moron%20de%20la%20frontera.2006-adquisicio%CC%81n%202011-527x527.jpg","4MTzF/XL4gHPRaRuMIyi+A==":"agustin-israel-algurugu-786x999.jpg","Leh5WOrLrrWGv+24kJiNig==":"agustin-israel-tondo-moron-786x999.jpg","XpnZ6Pe1/Cv/MKEQnFZqtQ==":"agustin-israel-capitan-nazareno-786x999.jpg","SgPggZ5fgEA1mbYnEgBigg==":"agustinisrael-abril-786x1062.jpg","6PUzKFeZtSa4c7rYmwnyqg==":"cartel%20arahal-2021-encargo%20festial%20algurugu%CC%81-786x1132.jpg","hqpTscZPQeJL3L8o08jKZg==":"agustin-israel-algurugu-1-786x999.jpg","AmjKe9SUSc9jEZ3W7KwWcA==":"agustin-israel-titan-786x999.jpg","62FPxi8M2/m7PSHz9h+fRA==":"agustin-israel-titan-detalle-691x878.jpg","sMbSUpuxRoWdm5gy0YAfTg==":"agustin-israel-pasion-couche-564x707.jpg","9uaXNNRu4lR/p2hR9IyqtQ==":"agustin-israel-sevilla-fashion-week-564x985.jpg","01Vzjt2woxvI4y34w4VO2g==":"agustin-israel-por-derecho-limite-flamenco-564x964.jpg","Bvpote12gxp0en0rBNHASw==":"agustin-israel-sevilla-fiestas-564x865.jpg","tD6z13PcHPyK6K7ShtIRyA==":"agustin-israel-fiestas-primavera-564x851.jpg","uTbQUPEKUWOPaQaZPnJFFQ==":"agustin-israel-serie-magenta-564x878.jpg","uND8obZs3Tx+hSrJ9TaVgw==":"agustin-israel-todos-tenemos.derecho-capirote-563x702.jpg","LafpDXD19hV9p2stdiIZiw==":"agustin-israel-vuelo.con-destino-563x366.jpg","Y3za3W5Mj3r0PHMy0ONwww==":"agustin-israel-mar%20de%20%20luz%20y%20pasion-564x667.jpg","upG7bpMdhBrymetdw/LOSQ==":"agustin-israel-sevilla-passion-week-462x559.jpg","rBqFFePaLW5JYhTKfWhhng==":"agustin-israel-sevilla-passion-week2-564x560.jpg","GQdsakSrPX7BhGOH90XWGg==":"agustin-israel-contacto-capirotes-563x797.jpg","EElH2g3AivEPvfH1hj5r8Q==":"agustin-israel-abril-564x704.jpg","NwpxeH7+XO/HqohO6OTnvg==":"agustin-israel-sevilla-fiestas-pintura-563x841.jpg","gW2DZhzEX4Z2FAxzn8ji3A==":"agustin-israel-sevilla-pop-563x842.jpg","QjL3ohC99lBCADCFp2BYBQ==":"agustin-israel-sevilla-pop-563x680.jpg","+nzo0pZQTX0e/8f/7ba81g==":"agustin-israel-selfies-564x663.jpg","8rr0/PhL0+oY4wyFm7hjkA==":"agustin-israel-oleos-416x856.jpg","xeBX4y+SYiX4TnPGq87jMg==":"agustin-israel-currografia-563x801.jpg","Lk7gOEuwIplQ2W8qv2QYxQ==":"agustin-israel-serie-in-564x701.jpg","vb/YiKzclvQmJRoHX9wcng==":"agustin-israel-otros-sacapuntas-564x795.jpg","TdMt+DCwN7pwLNVxuRS0cQ==":"agustin-israel-contacto-capirotes-1-563x797.jpg","fnhh8G5NepVLAD6JgrCAbg==":"agustin-israel-esculturas-564x722.jpg","Q69COYqZJIHaMdF5dT+iLw==":"agustin-israel-fotografia-564x806.jpg","k7BTP9xLBXMuHvbnGq2n9A==":"agustin-israel-este%20an%CC%83o%20playa-563x422.jpg","+sWVZl0/BuizLGFcqP6A/g==":"agustin-israel-codigo%20circulacion%20sevilla-537x537.jpg","T7FtmjXbRUMjt0w5tq0jQQ==":"agustin-israel-grabado-563x295.jpg","YvViWQhzr6uGvAANOGxjog==":"agustin-israel-grabado-563x295.jpeg","cnufmTDZWptBimvk5QERig==":"mbr-889x593.jpg","xAGrY0Zl7JorYmbA6A6nbg==":"mbr-889x889.png","yBrHj2n1H7SzQjri65N88g==":"mbr-889x488.jpg","KGvMmVskWtO14JmITA/a+w==":"agustin-israel-escaparatismo-564x423.jpg","dPgAM1wjPtjMLlK0N5aSOA==":"agustin-israel-capitan-nazareno-391x770.jpg","Tlc+qZIjRylPHvdQPGN6WA==":"agustin-israel-capitan-nazareno-feria-563x859.jpg","3SDs1D6JzHMKD3DrEgZ+2A==":"agustin-israel-capitan-nazareno-marco-563x641.jpg","J8aHG7pTei+st2VD8vR/OQ==":"886d4fcc1dd1b089107157e76aa12d70-563x558.jpg","hhP9dYq7FoWlwXXnf1h9sw==":"save%20the%20date-104x95.png","ggtTo/DC1l3Ev6V730A28g==":"background1-1.jpg","pG9NP0U8Ua2PUnty3pfetA==":"agustin-israel-sevilla-pop-563x680.jpeg","taBC9xIBL+NlNJ9Bl4gYzw==":"agustin-israel-sevilla-pop-1-563x680.jpeg","GzMSbfVsQMkvqizqf3udPg==":"agustin-israel-sevilla-pop-2-563x680.jpeg","UiHXKNbTr+fSzEAYvSg3lA==":"conference28-1920.jpg","R3mD+JhvcdC2b8GQv+Yn2w==":"agustin-israel-grafica-564x704.jpeg","io6Qxe1mil5GCEVyVJSilQ==":"agustinisrael-escultura-814x543.jpeg","8JYPc2lBqp/b/0PY0TXAdg==":"agustinisrael-haring-sevilla-sanlucar%20copia-1349x1932.jpeg","5eTblpazlwroNwwaaZ0I8w==":"la-razon-360x360.jpg","uco26OOmdW+q2n0F/oGb4Q==":"20-minutos-360x360.jpg","7CB4Y5n0aH+K98ni3/Gbvw==":"huelva-24-360x360.jpg","K/2gc8wa9w2hzV4pnx6Bkw==":"sevilla-secreta-360x360.jpg","isanhAjGkOtpPtD3SbgF7A==":"abc-360x360.jpg","94Pi0B/jEMF0SMx3po+1Fg==":"ultramarina-360x360.jpg","3hi0/3Ly8rlmw0P0eA4nMQ==":"sevilla-magazine-360x360.jpg","ogQFmwNzxZr/6wBjKDlIcQ==":"leonoticias-360x360.jpg"}